README.md
setup.py
micropython_octopuslab_installer.egg-info/PKG-INFO
micropython_octopuslab_installer.egg-info/SOURCES.txt
micropython_octopuslab_installer.egg-info/dependency_links.txt
micropython_octopuslab_installer.egg-info/requires.txt
micropython_octopuslab_installer.egg-info/top_level.txt
octopuslab_installer/__init__.py
octopuslab_installer/octopuslab_installer.py