Metadata-Version: 2.1
Name: micropython-octopuslab-installer
Version: 0.2.5
Summary: OctopusLab installer for MicroPython
Home-page: https://github.com/octopusengine/octopuslab-installer
Author: OctopusLAB
Author-email: info@octopuslab.cz
License: UNKNOWN
Platform: UNKNOWN
Classifier: Programming Language :: Python :: 3
Classifier: License :: OSI Approved :: MIT License
Classifier: Operating System :: OS Independent
Classifier: Development Status :: 4 - Beta
Requires-Python: >=3.6
